examples/__init__.py
examples/create_test_data.py
examples/higgs.py
examples/higgs_parquet.py
examples/readme.py
examples/readme_sklearn_api.py
examples/simple.py
examples/simple_dask.py
examples/simple_modin.py
examples/simple_objectstore.py
examples/simple_partitioned.py
examples/simple_predict.py
examples/simple_ray_dataset.py
examples/simple_tune.py
examples/train_on_test_data.py
examples/train_with_ml_dataset.py
xgboost_ray/__init__.py
xgboost_ray/callback.py
xgboost_ray/elastic.py
xgboost_ray/main.py
xgboost_ray/matrix.py
xgboost_ray/session.py
xgboost_ray/sklearn.py
xgboost_ray/tune.py
xgboost_ray/util.py
xgboost_ray/xgb.py
xgboost_ray/compat/__init__.py
xgboost_ray/compat/tracker.py
xgboost_ray/data_sources/__init__.py
xgboost_ray/data_sources/_distributed.py
xgboost_ray/data_sources/csv.py
xgboost_ray/data_sources/dask.py
xgboost_ray/data_sources/data_source.py
xgboost_ray/data_sources/modin.py
xgboost_ray/data_sources/numpy.py
xgboost_ray/data_sources/object_store.py
xgboost_ray/data_sources/pandas.py
xgboost_ray/data_sources/parquet.py
xgboost_ray/data_sources/partitioned.py
xgboost_ray/data_sources/petastorm.py
xgboost_ray/data_sources/ray_dataset.py
xgboost_ray/examples/__init__.py
xgboost_ray/examples/create_test_data.py
xgboost_ray/examples/higgs.py
xgboost_ray/examples/higgs_parquet.py
xgboost_ray/examples/readme.py
xgboost_ray/examples/readme_sklearn_api.py
xgboost_ray/examples/simple.py
xgboost_ray/examples/simple_dask.py
xgboost_ray/examples/simple_modin.py
xgboost_ray/examples/simple_objectstore.py
xgboost_ray/examples/simple_partitioned.py
xgboost_ray/examples/simple_predict.py
xgboost_ray/examples/simple_ray_dataset.py
xgboost_ray/examples/simple_tune.py
xgboost_ray/examples/train_on_test_data.py
xgboost_ray/examples/train_with_ml_dataset.py
xgboost_ray/tests/__init__.py
xgboost_ray/tests/conftest.py
xgboost_ray/tests/fault_tolerance.py
xgboost_ray/tests/test_client.py
xgboost_ray/tests/test_colocation.py
xgboost_ray/tests/test_data_source.py
xgboost_ray-0.1.19.dist-info/LICENSE
xgboost_ray-0.1.19.dist-info/METADATA
xgboost_ray-0.1.19.dist-info/WHEEL
xgboost_ray-0.1.19.dist-info/top_level.txt
xgboost_ray-0.1.19.dist-info/RECORD
