Metadata-Version: 2.1
Name: xgboost-ray
Version: 0.1.19
Summary: A Ray backend for distributed XGBoost
Home-page: https://github.com/ray-project/xgboost_ray
Author: Ray Team
Author-email: UNKNOWN
License: Apache 2.0
Platform: UNKNOWN
Requires-Dist: ray (>=2.7)
Requires-Dist: numpy (>=1.16)
Requires-Dist: pandas
Requires-Dist: wrapt (>=1.12.1)
Requires-Dist: xgboost (>=0.90)
Requires-Dist: packaging
